vnpt/__init__.py
vnpt/db_helper.py
vnpt/gis_helper.py
vnpt/spl_helper.py
vnpt/sql_helper.py
vnpt/engine/__init__.py
vnpt/engine/config.py
vnpt/engine/crud.py
VNPT-0.7.1.dist-info/LICENSE
VNPT-0.7.1.dist-info/METADATA
VNPT-0.7.1.dist-info/WHEEL
VNPT-0.7.1.dist-info/top_level.txt
VNPT-0.7.1.dist-info/RECORD
